{
  "BASE": "",
  "people": [
    {
      "nid": "Id",
      "title": "Name"
    },
    {
      "nid": "1",
      "title": "A1M"
    },
    {
      "nid": "2",
      "title": "A1F"
    },
    {
      "nid": "3",
      "title": "A2M"
    },
    {
      "nid": "4",
      "title": "A2F"
    },
    {
      "nid": "5",
      "title": "A3M"
    },
    {
      "nid": "6",
      "title": "A3F"
    },
    {
      "nid": "7",
      "title": "A4M"
    },
    {
      "nid": "8",
      "title": "A4F"
    },
    {
      "nid": "9",
      "title": "A5M"
    },
    {
      "nid": "10",
      "title": "A5F"
    },
    {
      "nid": "11",
      "title": "A6M"
    },
    {
      "nid": "12",
      "title": "A6F"
    },
    {
      "nid": "13",
      "title": "A7M"
    },
    {
      "nid": "14",
      "title": "A7F"
    },
    {
      "nid": "15",
      "title": "A8M"
    },
    {
      "nid": "16",
      "title": "A8F"
    },
    {
      "nid": "17",
      "title": "B1"
    },
    {
      "nid": "18",
      "title": "B2"
    },
    {
      "nid": "19",
      "title": "B3"
    },
    {
      "nid": "20",
      "title": "C1"
    },
    {
      "nid": "21",
      "title": "C2"
    },
    {
      "nid": "22",
      "title": "C3"
    },
    {
      "nid": "23",
      "title": "D1"
    },
    {
      "nid": "24",
      "title": "D2"
    },
    {
      "nid": "25",
      "title": "D3"
    },
    {
      "nid": "26",
      "title": "E1"
    },
    {
      "nid": "27",
      "title": "E2"
    },
    {
      "nid": "28",
      "title": "E3"
    },
    {
      "nid": "29",
      "title": "F1"
    },
    {
      "nid": "30",
      "title": "F2"
    },
    {
      "nid": "31",
      "title": "F3"
    },
    {
      "nid": "32",
      "title": "G1"
    },
    {
      "nid": "33",
      "title": "G2"
    },
    {
      "nid": "34",
      "title": "G3"
    },
    {
      "nid": "35",
      "title": "H1"
    },
    {
      "nid": "36",
      "title": "H2"
    },
    {
      "nid": "37",
      "title": "H3"
    },
    {
      "nid": "38",
      "title": "I1"
    },
    {
      "nid": "39",
      "title": "I2"
    },
    {
      "nid": "30",
      "title": "I3"
    },
    {
      "nid": "41",
      "title": "BC1"
    },
    {
      "nid": "42",
      "title": "BC2"
    },
    {
      "nid": "43",
      "title": "BC3"
    },
    {
      "nid": "44",
      "title": "DE1"
    },
    {
      "nid": "45",
      "title": "DE2"
    },
    {
      "nid": "46",
      "title": "DE3"
    },
    {
      "nid": "47",
      "title": "FG1"
    },
    {
      "nid": "48",
      "title": "FG2"
    },
    {
      "nid": "49",
      "title": "FG3"
    },
    {
      "nid": "50",
      "title": "HI1"
    },
    {
      "nid": "51",
      "title": "HI2"
    },
    {
      "nid": "52",
      "title": "HI3"
    },
    {
      "nid": "53",
      "title": "BCDE1"
    },
    {
      "nid": "54",
      "title": "BCDE2"
    },
    {
      "nid": "55",
      "title": "BCDE3"
    },
    {
      "nid": "56",
      "title": "FGHI1"
    },
    {
      "nid": "57",
      "title": "FGHI2"
    },
    {
      "nid": "58",
      "title": "FGHI3"
    },
    {
      "nid": "59",
      "title": "X1"
    },
    {
      "nid": "60",
      "title": "X2"
    },
    {
      "nid": "61",
      "title": "X3"
    },
    {
      "nid": "62",
      "title": "X4"
    },
    {
      "nid": "63",
      "title": "X5"
    },
    {
      "nid": "64",
      "title": "X6"
    },
    {
      "nid": "65",
      "title": "B1A"
    },
    {
      "nid": "66",
      "title": "B1B"
    },
    {
      "nid": "67",
      "title": "X7"
    },
    {
      "nid": "68",
      "title": "X8"
    },
    {
      "nid": "69",
      "title": "X9"
    },
    {
      "nid": "70",
      "title": "X10"
    },
    {
      "nid": "71",
      "title": "X11"
    },
    {
      "nid": "72",
      "title": "X12"
    },
    {
      "nid": "73",
      "title": "X13"
    },
    {
      "nid": "74",
      "title": "X14"
    },
    {
      "nid": "75",
      "title": "X15"
    },
    {
      "nid": "76",
      "title": "X16"
    },
    {
      "nid": "77",
      "title": "X17"
    }
  ],
  "births": [
    {
      "field_person_or_group_a_1": "Id",
      "field_event_year": "Birth"
    },
    {
      "field_person_or_group_a_1": "17",
      "field_event_year": "1755"
    },
    {
      "field_person_or_group_a_1": "18",
      "field_event_year": "1754"
    },
    {
      "field_person_or_group_a_1": "19",
      "field_event_year": "1753"
    },
    {
      "field_person_or_group_a_1": "41",
      "field_event_year": "1820"
    },
    {
      "field_person_or_group_a_1": "42",
      "field_event_year": "1810"
    },
    {
      "field_person_or_group_a_1": "43",
      "field_event_year": "1814"
    },
    {
      "field_person_or_group_a_1": "59",
      "field_event_year": "1950"
    },
    {
      "field_person_or_group_a_1": "60",
      "field_event_year": "1940"
    },
    {
      "field_person_or_group_a_1": "61",
      "field_event_year": "1960"
    },
    {
      "field_person_or_group_a_1": "62",
      "field_event_year": "1960"
    },
    {
      "field_person_or_group_a_1": "63",
      "field_event_year": "1940"
    },
    {
      "field_person_or_group_a_1": "64",
      "field_event_year": "1950"
    },
    {
      "field_person_or_group_a_1": "65",
      "field_event_year": "1948"
    },
    {
      "field_person_or_group_a_1": "66",
      "field_event_year": "1947"
    },
    {
      "field_person_or_group_a_1": "67",
      "field_event_year": "1951"
    },
    {
      "field_person_or_group_a_1": "68",
      "field_event_year": "1952"
    },
    {
      "field_person_or_group_a_1": "69",
      "field_event_year": "1953"
    },
    {
      "field_person_or_group_a_1": "70",
      "field_event_year": "1954"
    },
    {
      "field_person_or_group_a_1": "71",
      "field_event_year": "1955"
    },
    {
      "field_person_or_group_a_1": "72",
      "field_event_year": "1956"
    },
    {
      "field_person_or_group_a_1": "73",
      "field_event_year": "1957"
    },
    {
      "field_person_or_group_a_1": "74",
      "field_event_year": "1958"
    },
    {
      "field_person_or_group_a_1": "75",
      "field_event_year": "1959"
    },
    {
      "field_person_or_group_a_1": "76",
      "field_event_year": "1960"
    },
    {
      "field_person_or_group_a_1": "77",
      "field_event_year": "1961"
    }
  ],
  "gender": [
    {
      "field_person_or_group_a_1": "Id",
      "field_gender": "Gender"
    },
    {
      "field_person_or_group_a_1": "1",
      "field_gender": "M"
    },
    {
      "field_person_or_group_a_1": "2",
      "field_gender": "F"
    },
    {
      "field_person_or_group_a_1": "3",
      "field_gender": "M"
    },
    {
      "field_person_or_group_a_1": "4",
      "field_gender": "F"
    },
    {
      "field_person_or_group_a_1": "5",
      "field_gender": "M"
    },
    {
      "field_person_or_group_a_1": "6",
      "field_gender": "F"
    },
    {
      "field_person_or_group_a_1": "7",
      "field_gender": "M"
    },
    {
      "field_person_or_group_a_1": "8",
      "field_gender": "F"
    },
    {
      "field_person_or_group_a_1": "9",
      "field_gender": "M"
    },
    {
      "field_person_or_group_a_1": "10",
      "field_gender": "F"
    },
    {
      "field_person_or_group_a_1": "11",
      "field_gender": "M"
    },
    {
      "field_person_or_group_a_1": "12",
      "field_gender": "F"
    },
    {
      "field_person_or_group_a_1": "13",
      "field_gender": "M"
    },
    {
      "field_person_or_group_a_1": "14",
      "field_gender": "F"
    },
    {
      "field_person_or_group_a_1": "15",
      "field_gender": "M"
    },
    {
      "field_person_or_group_a_1": "16",
      "field_gender": "F"
    },
    {
      "field_person_or_group_a_1": "17",
      "field_gender": "F"
    },
    {
      "field_person_or_group_a_1": "18",
      "field_gender": "M"
    },
    {
      "field_person_or_group_a_1": "19",
      "field_gender": "F"
    },
    {
      "field_person_or_group_a_1": "20",
      "field_gender": "M"
    },
    {
      "field_person_or_group_a_1": "21",
      "field_gender": "F"
    },
    {
      "field_person_or_group_a_1": "22",
      "field_gender": "M"
    },
    {
      "field_person_or_group_a_1": "23",
      "field_gender": "F"
    },
    {
      "field_person_or_group_a_1": "24",
      "field_gender": "M"
    },
    {
      "field_person_or_group_a_1": "25",
      "field_gender": "F"
    },
    {
      "field_person_or_group_a_1": "26",
      "field_gender": "M"
    },
    {
      "field_person_or_group_a_1": "27",
      "field_gender": "F"
    },
    {
      "field_person_or_group_a_1": "28",
      "field_gender": "M"
    },
    {
      "field_person_or_group_a_1": "29",
      "field_gender": "F"
    },
    {
      "field_person_or_group_a_1": "30",
      "field_gender": "M"
    },
    {
      "field_person_or_group_a_1": "31",
      "field_gender": "F"
    },
    {
      "field_person_or_group_a_1": "32",
      "field_gender": "M"
    },
    {
      "field_person_or_group_a_1": "33",
      "field_gender": "F"
    },
    {
      "field_person_or_group_a_1": "34",
      "field_gender": "M"
    },
    {
      "field_person_or_group_a_1": "35",
      "field_gender": "F"
    },
    {
      "field_person_or_group_a_1": "36",
      "field_gender": "M"
    },
    {
      "field_person_or_group_a_1": "37",
      "field_gender": "F"
    },
    {
      "field_person_or_group_a_1": "38",
      "field_gender": "M"
    },
    {
      "field_person_or_group_a_1": "39",
      "field_gender": "F"
    },
    {
      "field_person_or_group_a_1": "30",
      "field_gender": "M"
    },
    {
      "field_person_or_group_a_1": "41",
      "field_gender": "F"
    },
    {
      "field_person_or_group_a_1": "42",
      "field_gender": "M"
    },
    {
      "field_person_or_group_a_1": "43",
      "field_gender": "F"
    },
    {
      "field_person_or_group_a_1": "44",
      "field_gender": "M"
    },
    {
      "field_person_or_group_a_1": "45",
      "field_gender": "F"
    },
    {
      "field_person_or_group_a_1": "46",
      "field_gender": "M"
    },
    {
      "field_person_or_group_a_1": "47",
      "field_gender": "F"
    },
    {
      "field_person_or_group_a_1": "48",
      "field_gender": "M"
    },
    {
      "field_person_or_group_a_1": "49",
      "field_gender": "F"
    },
    {
      "field_person_or_group_a_1": "50",
      "field_gender": "M"
    },
    {
      "field_person_or_group_a_1": "51",
      "field_gender": "F"
    },
    {
      "field_person_or_group_a_1": "52",
      "field_gender": "M"
    },
    {
      "field_person_or_group_a_1": "53",
      "field_gender": "F"
    },
    {
      "field_person_or_group_a_1": "54",
      "field_gender": "M"
    },
    {
      "field_person_or_group_a_1": "55",
      "field_gender": "F"
    },
    {
      "field_person_or_group_a_1": "56",
      "field_gender": "M"
    },
    {
      "field_person_or_group_a_1": "57",
      "field_gender": "F"
    },
    {
      "field_person_or_group_a_1": "58",
      "field_gender": "M"
    },
    {
      "field_person_or_group_a_1": "59",
      "field_gender": "F"
    },
    {
      "field_person_or_group_a_1": "60",
      "field_gender": "M"
    },
    {
      "field_person_or_group_a_1": "61",
      "field_gender": "F"
    },
    {
      "field_person_or_group_a_1": "62",
      "field_gender": "M"
    },
    {
      "field_person_or_group_a_1": "63",
      "field_gender": "F"
    },
    {
      "field_person_or_group_a_1": "64",
      "field_gender": "M"
    },
    {
      "field_person_or_group_a_1": "65",
      "field_gender": "F"
    },
    {
      "field_person_or_group_a_1": "66",
      "field_gender": "M"
    },
    {
      "field_person_or_group_a_1": "67",
      "field_gender": "M"
    },
    {
      "field_person_or_group_a_1": "68",
      "field_gender": "M"
    },
    {
      "field_person_or_group_a_1": "69",
      "field_gender": "M"
    },
    {
      "field_person_or_group_a_1": "70",
      "field_gender": "M"
    },
    {
      "field_person_or_group_a_1": "71",
      "field_gender": "M"
    },
    {
      "field_person_or_group_a_1": "72",
      "field_gender": "M"
    },
    {
      "field_person_or_group_a_1": "73",
      "field_gender": "M"
    },
    {
      "field_person_or_group_a_1": "74",
      "field_gender": "M"
    },
    {
      "field_person_or_group_a_1": "75",
      "field_gender": "M"
    },
    {
      "field_person_or_group_a_1": "76",
      "field_gender": "M"
    },
    {
      "field_person_or_group_a_1": "77",
      "field_gender": "M"
    }
  ],
  "relation": [
    {
      "field_person_or_group_a": "Id",
      "title": "Relation",
      "field_person_or_group_b": "Id2"
    },
    {
      "field_person_or_group_a": "1",
      "title": "Spouse Of",
      "field_person_or_group_b": "2"
    },
    {
      "field_person_or_group_a": "1",
      "title": "Parent Of",
      "field_person_or_group_b": "17"
    },
    {
      "field_person_or_group_a": "1",
      "title": "Parent Of",
      "field_person_or_group_b": "18"
    },
    {
      "field_person_or_group_a": "1",
      "title": "Parent Of",
      "field_person_or_group_b": "19"
    },
    {
      "field_person_or_group_a": "2",
      "title": "Parent Of",
      "field_person_or_group_b": "17"
    },
    {
      "field_person_or_group_a": "2",
      "title": "Parent Of",
      "field_person_or_group_b": "18"
    },
    {
      "field_person_or_group_a": "2",
      "title": "Parent Of",
      "field_person_or_group_b": "19"
    },
    {
      "field_person_or_group_a": "3",
      "title": "Spouse Of",
      "field_person_or_group_b": "4"
    },
    {
      "field_person_or_group_a": "3",
      "title": "Parent Of",
      "field_person_or_group_b": "20"
    },
    {
      "field_person_or_group_a": "3",
      "title": "Parent Of",
      "field_person_or_group_b": "21"
    },
    {
      "field_person_or_group_a": "3",
      "title": "Parent Of",
      "field_person_or_group_b": "22"
    },
    {
      "field_person_or_group_a": "4",
      "title": "Parent Of",
      "field_person_or_group_b": "20"
    },
    {
      "field_person_or_group_a": "4",
      "title": "Parent Of",
      "field_person_or_group_b": "21"
    },
    {
      "field_person_or_group_a": "4",
      "title": "Parent Of",
      "field_person_or_group_b": "22"
    },
    {
      "field_person_or_group_a": "5",
      "title": "Spouse Of",
      "field_person_or_group_b": "6"
    },
    {
      "field_person_or_group_a": "5",
      "title": "Parent Of",
      "field_person_or_group_b": "23"
    },
    {
      "field_person_or_group_a": "5",
      "title": "Parent Of",
      "field_person_or_group_b": "24"
    },
    {
      "field_person_or_group_a": "5",
      "title": "Parent Of",
      "field_person_or_group_b": "25"
    },
    {
      "field_person_or_group_a": "6",
      "title": "Parent Of",
      "field_person_or_group_b": "23"
    },
    {
      "field_person_or_group_a": "6",
      "title": "Parent Of",
      "field_person_or_group_b": "24"
    },
    {
      "field_person_or_group_a": "6",
      "title": "Parent Of",
      "field_person_or_group_b": "25"
    },
    {
      "field_person_or_group_a": "7",
      "title": "Spouse Of",
      "field_person_or_group_b": "8"
    },
    {
      "field_person_or_group_a": "7",
      "title": "Parent Of",
      "field_person_or_group_b": "26"
    },
    {
      "field_person_or_group_a": "7",
      "title": "Parent Of",
      "field_person_or_group_b": "27"
    },
    {
      "field_person_or_group_a": "7",
      "title": "Parent Of",
      "field_person_or_group_b": "28"
    },
    {
      "field_person_or_group_a": "8",
      "title": "Parent Of",
      "field_person_or_group_b": "26"
    },
    {
      "field_person_or_group_a": "8",
      "title": "Parent Of",
      "field_person_or_group_b": "27"
    },
    {
      "field_person_or_group_a": "8",
      "title": "Parent Of",
      "field_person_or_group_b": "28"
    },
    {
      "field_person_or_group_a": "9",
      "title": "Spouse Of",
      "field_person_or_group_b": "10"
    },
    {
      "field_person_or_group_a": "9",
      "title": "Parent Of",
      "field_person_or_group_b": "29"
    },
    {
      "field_person_or_group_a": "9",
      "title": "Parent Of",
      "field_person_or_group_b": "30"
    },
    {
      "field_person_or_group_a": "9",
      "title": "Parent Of",
      "field_person_or_group_b": "31"
    },
    {
      "field_person_or_group_a": "10",
      "title": "Parent Of",
      "field_person_or_group_b": "29"
    },
    {
      "field_person_or_group_a": "10",
      "title": "Parent Of",
      "field_person_or_group_b": "30"
    },
    {
      "field_person_or_group_a": "10",
      "title": "Parent Of",
      "field_person_or_group_b": "31"
    },
    {
      "field_person_or_group_a": "11",
      "title": "Spouse Of",
      "field_person_or_group_b": "12"
    },
    {
      "field_person_or_group_a": "11",
      "title": "Parent Of",
      "field_person_or_group_b": "32"
    },
    {
      "field_person_or_group_a": "11",
      "title": "Parent Of",
      "field_person_or_group_b": "33"
    },
    {
      "field_person_or_group_a": "11",
      "title": "Parent Of",
      "field_person_or_group_b": "34"
    },
    {
      "field_person_or_group_a": "12",
      "title": "Parent Of",
      "field_person_or_group_b": "32"
    },
    {
      "field_person_or_group_a": "12",
      "title": "Parent Of",
      "field_person_or_group_b": "33"
    },
    {
      "field_person_or_group_a": "12",
      "title": "Parent Of",
      "field_person_or_group_b": "34"
    },
    {
      "field_person_or_group_a": "13",
      "title": "Spouse Of",
      "field_person_or_group_b": "14"
    },
    {
      "field_person_or_group_a": "13",
      "title": "Parent Of",
      "field_person_or_group_b": "35"
    },
    {
      "field_person_or_group_a": "13",
      "title": "Parent Of",
      "field_person_or_group_b": "36"
    },
    {
      "field_person_or_group_a": "13",
      "title": "Parent Of",
      "field_person_or_group_b": "37"
    },
    {
      "field_person_or_group_a": "14",
      "title": "Parent Of",
      "field_person_or_group_b": "35"
    },
    {
      "field_person_or_group_a": "14",
      "title": "Parent Of",
      "field_person_or_group_b": "36"
    },
    {
      "field_person_or_group_a": "14",
      "title": "Parent Of",
      "field_person_or_group_b": "37"
    },
    {
      "field_person_or_group_a": "15",
      "title": "Spouse Of",
      "field_person_or_group_b": "16"
    },
    {
      "field_person_or_group_a": "15",
      "title": "Parent Of",
      "field_person_or_group_b": "38"
    },
    {
      "field_person_or_group_a": "15",
      "title": "Parent Of",
      "field_person_or_group_b": "39"
    },
    {
      "field_person_or_group_a": "15",
      "title": "Parent Of",
      "field_person_or_group_b": "40"
    },
    {
      "field_person_or_group_a": "16",
      "title": "Parent Of",
      "field_person_or_group_b": "38"
    },
    {
      "field_person_or_group_a": "16",
      "title": "Parent Of",
      "field_person_or_group_b": "39"
    },
    {
      "field_person_or_group_a": "16",
      "title": "Parent Of",
      "field_person_or_group_b": "40"
    },
    {
      "field_person_or_group_a": "17",
      "title": "Spouse Of",
      "field_person_or_group_b": "20"
    },
    {
      "field_person_or_group_a": "17",
      "title": "Parent Of",
      "field_person_or_group_b": "41"
    },
    {
      "field_person_or_group_a": "17",
      "title": "Parent Of",
      "field_person_or_group_b": "42"
    },
    {
      "field_person_or_group_a": "17",
      "title": "Parent Of",
      "field_person_or_group_b": "43"
    },
    {
      "field_person_or_group_a": "20",
      "title": "Parent Of",
      "field_person_or_group_b": "41"
    },
    {
      "field_person_or_group_a": "20",
      "title": "Parent Of",
      "field_person_or_group_b": "42"
    },
    {
      "field_person_or_group_a": "20",
      "title": "Parent Of",
      "field_person_or_group_b": "43"
    },
    {
      "field_person_or_group_a": "23",
      "title": "Spouse Of",
      "field_person_or_group_b": "26"
    },
    {
      "field_person_or_group_a": "23",
      "title": "Parent Of",
      "field_person_or_group_b": "44"
    },
    {
      "field_person_or_group_a": "23",
      "title": "Parent Of",
      "field_person_or_group_b": "45"
    },
    {
      "field_person_or_group_a": "23",
      "title": "Parent Of",
      "field_person_or_group_b": "46"
    },
    {
      "field_person_or_group_a": "26",
      "title": "Parent Of",
      "field_person_or_group_b": "44"
    },
    {
      "field_person_or_group_a": "26",
      "title": "Parent Of",
      "field_person_or_group_b": "45"
    },
    {
      "field_person_or_group_a": "26",
      "title": "Parent Of",
      "field_person_or_group_b": "46"
    },
    {
      "field_person_or_group_a": "29",
      "title": "Spouse Of",
      "field_person_or_group_b": "32"
    },
    {
      "field_person_or_group_a": "29",
      "title": "Parent Of",
      "field_person_or_group_b": "47"
    },
    {
      "field_person_or_group_a": "29",
      "title": "Parent Of",
      "field_person_or_group_b": "48"
    },
    {
      "field_person_or_group_a": "29",
      "title": "Parent Of",
      "field_person_or_group_b": "49"
    },
    {
      "field_person_or_group_a": "32",
      "title": "Parent Of",
      "field_person_or_group_b": "47"
    },
    {
      "field_person_or_group_a": "32",
      "title": "Parent Of",
      "field_person_or_group_b": "48"
    },
    {
      "field_person_or_group_a": "32",
      "title": "Parent Of",
      "field_person_or_group_b": "49"
    },
    {
      "field_person_or_group_a": "35",
      "title": "Spouse Of",
      "field_person_or_group_b": "38"
    },
    {
      "field_person_or_group_a": "35",
      "title": "Parent Of",
      "field_person_or_group_b": "50"
    },
    {
      "field_person_or_group_a": "35",
      "title": "Parent Of",
      "field_person_or_group_b": "51"
    },
    {
      "field_person_or_group_a": "35",
      "title": "Parent Of",
      "field_person_or_group_b": "52"
    },
    {
      "field_person_or_group_a": "38",
      "title": "Parent Of",
      "field_person_or_group_b": "50"
    },
    {
      "field_person_or_group_a": "38",
      "title": "Parent Of",
      "field_person_or_group_b": "51"
    },
    {
      "field_person_or_group_a": "38",
      "title": "Parent Of",
      "field_person_or_group_b": "52"
    },
    {
      "field_person_or_group_a": "41",
      "title": "Spouse Of",
      "field_person_or_group_b": "44"
    },
    {
      "field_person_or_group_a": "41",
      "title": "Parent Of",
      "field_person_or_group_b": "53"
    },
    {
      "field_person_or_group_a": "41",
      "title": "Parent Of",
      "field_person_or_group_b": "54"
    },
    {
      "field_person_or_group_a": "41",
      "title": "Parent Of",
      "field_person_or_group_b": "55"
    },
    {
      "field_person_or_group_a": "44",
      "title": "Parent Of",
      "field_person_or_group_b": "53"
    },
    {
      "field_person_or_group_a": "44",
      "title": "Parent Of",
      "field_person_or_group_b": "54"
    },
    {
      "field_person_or_group_a": "44",
      "title": "Parent Of",
      "field_person_or_group_b": "55"
    },
    {
      "field_person_or_group_a": "47",
      "title": "Spouse Of",
      "field_person_or_group_b": "50"
    },
    {
      "field_person_or_group_a": "47",
      "title": "Parent Of",
      "field_person_or_group_b": "56"
    },
    {
      "field_person_or_group_a": "47",
      "title": "Parent Of",
      "field_person_or_group_b": "57"
    },
    {
      "field_person_or_group_a": "47",
      "title": "Parent Of",
      "field_person_or_group_b": "58"
    },
    {
      "field_person_or_group_a": "50",
      "title": "Parent Of",
      "field_person_or_group_b": "56"
    },
    {
      "field_person_or_group_a": "50",
      "title": "Parent Of",
      "field_person_or_group_b": "57"
    },
    {
      "field_person_or_group_a": "50",
      "title": "Parent Of",
      "field_person_or_group_b": "58"
    },
    {
      "field_person_or_group_a": "53",
      "title": "Spouse Of",
      "field_person_or_group_b": "56"
    },
    {
      "field_person_or_group_a": "53",
      "title": "Parent Of",
      "field_person_or_group_b": "59"
    },
    {
      "field_person_or_group_a": "53",
      "title": "Parent Of",
      "field_person_or_group_b": "60"
    },
    {
      "field_person_or_group_a": "53",
      "title": "Parent Of",
      "field_person_or_group_b": "61"
    },
    {
      "field_person_or_group_a": "56",
      "title": "Parent Of",
      "field_person_or_group_b": "59"
    },
    {
      "field_person_or_group_a": "56",
      "title": "Parent Of",
      "field_person_or_group_b": "60"
    },
    {
      "field_person_or_group_a": "56",
      "title": "Parent Of",
      "field_person_or_group_b": "61"
    },
    {
      "field_person_or_group_a": "54",
      "title": "Spouse Of",
      "field_person_or_group_b": "57"
    },
    {
      "field_person_or_group_a": "55",
      "title": "Spouse Of",
      "field_person_or_group_b": "58"
    },
    {
      "field_person_or_group_a": "54",
      "title": "Parent Of",
      "field_person_or_group_b": "62"
    },
    {
      "field_person_or_group_a": "54",
      "title": "Parent Of",
      "field_person_or_group_b": "63"
    },
    {
      "field_person_or_group_a": "54",
      "title": "Parent Of",
      "field_person_or_group_b": "64"
    },
    {
      "field_person_or_group_a": "57",
      "title": "Parent Of",
      "field_person_or_group_b": "62"
    },
    {
      "field_person_or_group_a": "57",
      "title": "Parent Of",
      "field_person_or_group_b": "63"
    },
    {
      "field_person_or_group_a": "57",
      "title": "Parent Of",
      "field_person_or_group_b": "64"
    },
    {
      "field_person_or_group_a": "41",
      "title": "Spouse Of",
      "field_person_or_group_b": "45"
    },
    {
      "field_person_or_group_a": "41",
      "title": "Spouse Of",
      "field_person_or_group_b": "46"
    },
    {
      "field_person_or_group_a": "42",
      "title": "Spouse Of",
      "field_person_or_group_b": "46"
    },
    {
      "field_person_or_group_a": "44",
      "title": "Spouse Of",
      "field_person_or_group_b": "66"
    },
    {
      "field_person_or_group_a": "66",
      "title": "Spouse Of",
      "field_person_or_group_b": "44"
    },
    {
      "field_person_or_group_a": "1",
      "title": "Parent Of",
      "field_person_or_group_b": "65"
    },
    {
      "field_person_or_group_a": "1",
      "title": "Parent Of",
      "field_person_or_group_b": "66"
    },
    {
      "field_person_or_group_a": "3",
      "title": "Parent Of",
      "field_person_or_group_b": "65"
    },
    {
      "field_person_or_group_a": "5",
      "title": "Parent Of",
      "field_person_or_group_b": "66"
    },
    {
      "field_person_or_group_a": "1",
      "title": "Parent Of",
      "field_person_or_group_b": "67"
    },
    {
      "field_person_or_group_a": "3",
      "title": "Parent Of",
      "field_person_or_group_b": "67"
    },
    {
      "field_person_or_group_a": "1",
      "title": "Parent Of",
      "field_person_or_group_b": "68"
    },
    {
      "field_person_or_group_a": "3",
      "title": "Parent Of",
      "field_person_or_group_b": "68"
    },
    {
      "field_person_or_group_a": "1",
      "title": "Parent Of",
      "field_person_or_group_b": "69"
    },
    {
      "field_person_or_group_a": "3",
      "title": "Parent Of",
      "field_person_or_group_b": "69"
    },
    {
      "field_person_or_group_a": "1",
      "title": "Parent Of",
      "field_person_or_group_b": "70"
    },
    {
      "field_person_or_group_a": "3",
      "title": "Parent Of",
      "field_person_or_group_b": "70"
    },
    {
      "field_person_or_group_a": "1",
      "title": "Parent Of",
      "field_person_or_group_b": "71"
    },
    {
      "field_person_or_group_a": "3",
      "title": "Parent Of",
      "field_person_or_group_b": "71"
    },
    {
      "field_person_or_group_a": "1",
      "title": "Parent Of",
      "field_person_or_group_b": "72"
    },
    {
      "field_person_or_group_a": "3",
      "title": "Parent Of",
      "field_person_or_group_b": "72"
    },
    {
      "field_person_or_group_a": "1",
      "title": "Parent Of",
      "field_person_or_group_b": "73"
    },
    {
      "field_person_or_group_a": "3",
      "title": "Parent Of",
      "field_person_or_group_b": "73"
    },
    {
      "field_person_or_group_a": "1",
      "title": "Parent Of",
      "field_person_or_group_b": "74"
    },
    {
      "field_person_or_group_a": "3",
      "title": "Parent Of",
      "field_person_or_group_b": "74"
    },
    {
      "field_person_or_group_a": "1",
      "title": "Parent Of",
      "field_person_or_group_b": "75"
    },
    {
      "field_person_or_group_a": "3",
      "title": "Parent Of",
      "field_person_or_group_b": "75"
    },
    {
      "field_person_or_group_a": "1",
      "title": "Parent Of",
      "field_person_or_group_b": "76"
    },
    {
      "field_person_or_group_a": "3",
      "title": "Parent Of",
      "field_person_or_group_b": "76"
    },
    {
      "field_person_or_group_a": "1",
      "title": "Parent Of",
      "field_person_or_group_b": "77"
    },
    {
      "field_person_or_group_a": "3",
      "title": "Parent Of",
      "field_person_or_group_b": "77"
    }
  ],
  "deaths": [
    {
      "field_person_or_group_a_1": "Id",
      "field_event_year": "Death"
    },
    {
      "field_person_or_group_a_1": "17",
      "field_event_year": "1833"
    },
    {
      "field_person_or_group_a_1": "18",
      "field_event_year": "1834"
    },
    {
      "field_person_or_group_a_1": "19",
      "field_event_year": "1833"
    },
    {
      "field_person_or_group_a_1": "41",
      "field_event_year": "1844"
    },
    {
      "field_person_or_group_a_1": "42",
      "field_event_year": "1877"
    },
    {
      "field_person_or_group_a_1": "43",
      "field_event_year": "1866"
    }
  ]
}
